Week 2/Circuit 1/circuit1.v
module simple_circuit(A,B,C,Y);

input A,B,C;

output Y;

wire w1;

assign w1=B&C;
assign Y=A|w1;

endmodule

Week 2/Circuit 1/tb_circuit1.v
module tb_simple_circuit;

reg A,B,C;

simple_circuit M1(A,B,C,Y);

initial

begin

A=1'b0 ; B=1'b0 ; C=1'b0;
#20
A=1'b0 ; B=1'b0 ; C=1'b1;
#20
A=1'b0 ; B=1'b1 ; C=1'b0;
#20
A=1'b0 ; B=1'b1 ; C=1'b1;
#20
A=1'b1 ; B=1'b0 ; C=1'b0;
#20
A=1'b1 ; B=1'b0 ; C=1'b1;
#20
A=1'b1 ; B=1'b1 ; C=1'b0;
#20
A=1'b1 ; B=1'b1 ; C=1'b1;

end


initial
begin
$monitor($time, "A=%b, B=%b, C=%b,Y=%b", A,B,C,Y);
end
initial
begin
$dumpfile ("circuit1.vcd");
 $dumpvars (0, tb_simple_circuit);
end
endmodule

Week 2/Circuit 1/circuit1.vcd
$date
	Thu Aug 17 14:48:28 2023
$end
$version
	Icarus Verilog
$end
$timescale
	1s
$end
$scope module tb_simple_circuit $end
$var wire 1 ! Y $end
$var reg 1 " A $end
$var reg 1 # B $end
$var reg 1 $ C $end
$scope module M1 $end
$var wire 1 " A $end
$var wire 1 # B $end
$var wire 1 $ C $end
$var wire 1 ! Y $end
$var wire 1 % w1 $end
$upscope $end
$upscope $end
$enddefinitions $end
$comment Show the parameter values. $end
$dumpall
$end
#0
$dumpvars
0%
0$
0#
0"
0!
$end
#20
1$
#40
0$
1#
#60
1!
1%
1$
#80
0%
0$
0#
1"
#100
1$
#120
0$
1#
#140
1%
1$
