Week 3/basic.v
module invert(input wire i, output wire o1);	
assign o1 = !i;
endmodule
module and2(input wire i0, i1, output wire o2);
assign o2 = i0 & i1;
endmodule
module or2(input wire i0, i1, output wire o3);
assign o3 = i0 | i1;	
endmodule	
module xor2(input wire i0, i1, output wire o4);
assign o4 = i0 ^ i1;	
endmodule
module nand2(input wire i0, i1, output wire o5);	
wire t;
and2 and2_0 (i0, i1, t);	
invert invert_0 (t, o5);
endmodule

Week 3/fulladder.v
module fulladd(input wire a, b, cin, output wire sum, cout);
wire [4:0] t;    
xor2 x0(a,b,t[0]);   
xor2 x1(cin,t[0],sum); 
and2 a0(a,b,t[1]);    
and2 a1(a,cin,t[2]);
and2 a2(b,cin,t[3]);   
or2 o0(t[1],t[2],t[4]);    
or2 o1(t[4],t[3],cout);
endmodule

Week 3/rca.v
// Module 4-bit ripple carry adder
module fulladdR(input wire [3:0] a, b, input wire cin, output wire [3:0] sum, output wire cout);  
 // Instantiate full adder modules here
wire [2:0] c;  
fulladd u0(a[0],b[0],cin,sum[0],c[0]);  
fulladd u1(a[1],b[1],c[0],sum[1],c[1]);  
fulladd u2(a[2],b[2],c[1],sum[2],c[2]);  
fulladd u3(a[3],b[3],c[2],sum[3],cout);
endmodule

Week 3/rca_tb.v
`timescale 1 ns / 100 ps
`define TESTVECS 10
module tb;  
reg clk, reset; 
 reg [3:0] i0, i1;
 reg cin;  
wire [3:0] o; 
wire cout; 
 reg [8:0] test_vecs [0:(`TESTVECS-1)];  
integer i; 
initial 
begin 
$dumpfile("rca_test.vcd"); 
$dumpvars(0,tb);  
 end  
initial 
begin
 reset = 1'b1; #12.5 reset = 1'b0; end  initial clk = 1'b0; always #5 clk =~ clk;
  initial begin   
 test_vecs[0] = 9'b000000000;   
 test_vecs[1] = 9'b000000001; 
test_vecs[2] = 9'b000100010;  
  test_vecs[3] = 9'b000100011;    
test_vecs[4] = 9'b001000100;  
  test_vecs[5] = 9'b001000101;  
  test_vecs[6] = 9'b101010110; 
   test_vecs[7] = 9'b101010111;
test_vecs[8] = 9'b111011110;
test_vecs[9] = 9'b111011111;
  end 
initial {i0, i1, cin, i} = 0; 
 fulladdR u0 (i0, i1, cin, o, cout);  
initial begin    #6 
for(i=0;i<`TESTVECS;i=i+1)   
   begin #10 {i0, i1, cin}=test_vecs[i]; 
end    #100 $finish;  end
always@(i0 or i1 or cin)
$monitor("At time = %t, i0=%b, i1=%b,cin=%b,Sum = %b,Carry %b", $time,i0,i1,cin,o,cout);
endmodule

Week 3/rca_test.vcd
$date
	Thu Aug 24 14:57:27 2023
$end
$version
	Icarus Verilog
$end
$timescale
	100ps
$end
$scope module tb $end
$var wire 4 ! o [3:0] $end
$var wire 1 " cout $end
$var reg 1 # cin $end
$var reg 1 $ clk $end
$var reg 4 % i0 [3:0] $end
$var reg 4 & i1 [3:0] $end
$var reg 1 ' reset $end
$var integer 32 ( i [31:0] $end
$scope module u0 $end
$var wire 4 ) a [3:0] $end
$var wire 4 * b [3:0] $end
$var wire 1 # cin $end
$var wire 4 + sum [3:0] $end
$var wire 1 " cout $end
$var wire 3 , c [2:0] $end
$scope module u0 $end
$var wire 1 - a $end
$var wire 1 . b $end
$var wire 1 # cin $end
$var wire 5 / t [4:0] $end
$var wire 1 0 sum $end
$var wire 1 1 cout $end
$scope module a0 $end
$var wire 1 - i0 $end
$var wire 1 . i1 $end
$var wire 1 2 o2 $end
$upscope $end
$scope module a1 $end
$var wire 1 - i0 $end
$var wire 1 # i1 $end
$var wire 1 3 o2 $end
$upscope $end
$scope module a2 $end
$var wire 1 . i0 $end
$var wire 1 # i1 $end
$var wire 1 4 o2 $end
$upscope $end
$scope module o0 $end
$var wire 1 5 i0 $end
$var wire 1 6 i1 $end
$var wire 1 7 o3 $end
$upscope $end
$scope module o1 $end
$var wire 1 8 i0 $end
$var wire 1 9 i1 $end
$var wire 1 1 o3 $end
$upscope $end
$scope module x0 $end
$var wire 1 - i0 $end
$var wire 1 . i1 $end
$var wire 1 : o4 $end
$upscope $end
$scope module x1 $end
$var wire 1 ; i0 $end
$var wire 1 # i1 $end
$var wire 1 0 o4 $end
$upscope $end
$upscope $end
$scope module u1 $end
$var wire 1 < a $end
$var wire 1 = b $end
$var wire 1 > cin $end
$var wire 5 ? t [4:0] $end
$var wire 1 @ sum $end
$var wire 1 A cout $end
$scope module a0 $end
$var wire 1 < i0 $end
$var wire 1 = i1 $end
$var wire 1 B o2 $end
$upscope $end
$scope module a1 $end
$var wire 1 < i0 $end
$var wire 1 > i1 $end
$var wire 1 C o2 $end
$upscope $end
$scope module a2 $end
$var wire 1 = i0 $end
$var wire 1 > i1 $end
$var wire 1 D o2 $end
$upscope $end
$scope module o0 $end
$var wire 1 E i0 $end
$var wire 1 F i1 $end
$var wire 1 G o3 $end
$upscope $end
$scope module o1 $end
$var wire 1 H i0 $end
$var wire 1 I i1 $end
$var wire 1 A o3 $end
$upscope $end
$scope module x0 $end
$var wire 1 < i0 $end
$var wire 1 = i1 $end
$var wire 1 J o4 $end
$upscope $end
$scope module x1 $end
$var wire 1 K i0 $end
$var wire 1 > i1 $end
$var wire 1 @ o4 $end
$upscope $end
$upscope $end
$scope module u2 $end
$var wire 1 L a $end
$var wire 1 M b $end
$var wire 1 N cin $end
$var wire 5 O t [4:0] $end
$var wire 1 P sum $end
$var wire 1 Q cout $end
$scope module a0 $end
$var wire 1 L i0 $end
$var wire 1 M i1 $end
$var wire 1 R o2 $end
$upscope $end
$scope module a1 $end
$var wire 1 L i0 $end
$var wire 1 N i1 $end
$var wire 1 S o2 $end
$upscope $end
$scope module a2 $end
$var wire 1 M i0 $end
$var wire 1 N i1 $end
$var wire 1 T o2 $end
$upscope $end
$scope module o0 $end
$var wire 1 U i0 $end
$var wire 1 V i1 $end
$var wire 1 W o3 $end
$upscope $end
$scope module o1 $end
$var wire 1 X i0 $end
$var wire 1 Y i1 $end
$var wire 1 Q o3 $end
$upscope $end
$scope module x0 $end
$var wire 1 L i0 $end
$var wire 1 M i1 $end
$var wire 1 Z o4 $end
$upscope $end
$scope module x1 $end
$var wire 1 [ i0 $end
$var wire 1 N i1 $end
$var wire 1 P o4 $end
$upscope $end
$upscope $end
$scope module u3 $end
$var wire 1 \ a $end
$var wire 1 ] b $end
$var wire 1 ^ cin $end
$var wire 5 _ t [4:0] $end
$var wire 1 ` sum $end
$var wire 1 " cout $end
$scope module a0 $end
$var wire 1 \ i0 $end
$var wire 1 ] i1 $end
$var wire 1 a o2 $end
$upscope $end
$scope module a1 $end
$var wire 1 \ i0 $end
$var wire 1 ^ i1 $end
$var wire 1 b o2 $end
$upscope $end
$scope module a2 $end
$var wire 1 ] i0 $end
$var wire 1 ^ i1 $end
$var wire 1 c o2 $end
$upscope $end
$scope module o0 $end
$var wire 1 d i0 $end
$var wire 1 e i1 $end
$var wire 1 f o3 $end
$upscope $end
$scope module o1 $end
$var wire 1 g i0 $end
$var wire 1 h i1 $end
$var wire 1 " o3 $end
$upscope $end
$scope module x0 $end
$var wire 1 \ i0 $end
$var wire 1 ] i1 $end
$var wire 1 i o4 $end
$upscope $end
$scope module x1 $end
$var wire 1 j i0 $end
$var wire 1 ^ i1 $end
$var wire 1 ` o4 $end
$upscope $end
$upscope $end
$upscope $end
$upscope $end
$enddefinitions $end
$comment Show the parameter values. $end
$dumpall
$end
#0
$dumpvars
0j
0i
0h
0g
0f
0e
0d
0c
0b
0a
0`
b0 _
0^
0]
0\
0[
0Z
0Y
0X
0W
0V
0U
0T
0S
0R
0Q
0P
b0 O
0N
0M
0L
0K
0J
0I
0H
0G
0F
0E
0D
0C
0B
0A
0@
b0 ?
0>
0=
0<
0;
0:
09
08
07
06
05
04
03
02
01
00
b0 /
0.
0-
b0 ,
b0 +
b0 *
b0 )
b0 (
1'
b0 &
b0 %
0$
0#
0"
b0 !
$end
#50
1$
#100
0$
#125
0'
#150
1$
#160
b1 (
#200
0$
#250
1$
#260
b1 !
b1 +
10
b10 (
1#
#300
0$
#350
1$
#360
1@
1>
b1 ,
11
19
17
15
b10010 /
12
1-
1.
b10 !
b10 +
00
b11 (
b1 %
b1 )
b1 &
b1 *
0#
#400
0$
#450
1$
#460
16
18
13
b11110 /
14
b11 !
b11 +
10
b100 (
1#
#500
0$
#550
1$
#560
0@
0>
01
1P
09
1I
1N
07
1G
b10 ,
1A
0F
05
1E
0H
0C
02
1B
b10010 ?
0D
06
08
0-
1<
0.
1=
03
b0 /
04
b100 !
b100 +
00
b101 (
b10 %
b10 )
b10 &
b10 *
0#
#600
0$
#650
1$
#660
b101 !
b101 +
10
b110 (
1#
#700
0$
#750
1$
#760
1"
1h
1f
1;
1d
b1 /
1:
b10010 _
1a
1\
1.
1]
b101 !
b101 +
10
b111 (
b1010 %
b1010 )
b1011 &
b1011 *
0#
#800
0$
#850
1$
#860
1F
1H
1C
b11110 ?
1D
1@
1>
b11 ,
11
18
b1001 /
14
b110 !
b110 +
00
b1000 (
1#
#900
0$
#950
1$
#960
1e
1g
1b
b11110 _
1c
1`
0F
0H
1Y
1^
0C
b10010 ?
0D
0@
1W
1Q
0>
1V
1U
1X
b110 ,
01
1S
1R
b11110 O
1T
08
1L
1M
b1 /
04
b1101 !
b1101 +
10
b1001 (
b1110 %
b1110 )
b1111 &
b1111 *
0#
#1000
0$
#1050
1$
#1060
1F
1H
1C
b11110 ?
1D
1@
1>
b111 ,
11
18
b1001 /
14
b1110 !
b1110 +
00
b1010 (
1#
